{"location ": "N. Whatley Rd. Cemetery", "latitude ": "33.1026219", "longitude ": "-85.1866095", "description ": "The Cemetery dates bake to the 1800's. a strange stillness is at the cemetery. Reports of hear screams if you knock 3 times on the large marker in the middle of the cemetery. Dogs react violently to the place and apparitions have been reported.", "state_abbrev ": "GA", "city_latitude": "33.0698575", "country ": "United States", "id": "d219f4fa-c1ba-411c-a73c-6287e9096541", "city ": "Troup County", "state ": "Georgia", "city_longitude ": "-85.02334599999999", "jaccard_score": 0.00017297773304818215}