{"id": "bf3a7d36-0b49-40ae-8ab2-05c3e67b23f0", "location ": "Daytona Playhouse", "city ": "Daytona", "longitude ": "-81.02090799999999", "state ": "Florida", "country ": "United States", "latitude ": "29.238215", "city_longitude ": "-81.0228331", "state_abbrev ": "FL", "city_latitude": "29.2108147", "description ": "Two people haunt the playhouse. Their names are unknown but we know it is a man and woman. The man died fighting a war in Spain and when the woman could wait no longer for him to return, she committed suicide. She was pregnant. She dove into the Halifax River killing her and her unborn child.", "jaccard_score": 0.00017297773304818215}