{"city_latitude": "39.9978764", "city ": "Millersville", "longitude ": "-76.3580515", "id": "2283d5de-a1c2-48b7-83e6-506dcb73b95f", "state_abbrev ": "PA", "latitude ": "39.9692317", "description ": "The story goes that a man lived across from the old bridge and one day he just snapped and hung his family from the bridge rafters.\u00a0 Reports of apparitions appearing on photos, voices being heard, and a feeling of being watched.", "country ": "United States", "city_longitude ": "-76.3541274", "location ": "Long Lane Bridge", "state ": "Pennsylvania", "jaccard_score": 0.00017297773304818215}