{"state ": "Missouri", "city ": "St. Louis", "location ": "downtown", "id": "0bb0f1c7-a62c-4cff-b9cb-53113fb58af4", "country ": "United States", "city_longitude ": "-90.1994042", "longitude ": "-90.1916501", "city_latitude": "38.6270025", "description ": "Powell Symphony Hall - The Powell ghost (dubbed \"George\" by stagehands) makes noises, plays with the lights and elevator, and is sometimes seen as a man in a white suit and white hat. He is thought to be a former vaudevillian.", "state_abbrev ": "MO", "latitude ": "38.6266074", "jaccard_score": 0.00017297773304818215}