{"city_latitude": "44.4582983", "state ": "Minnesota", "location ": "St. Olaf College", "city ": "Northfield", "city_longitude ": "-93.161604", "id": "0c998668-0853-44dd-a954-2258216474aa", "description ": "Hilleboe Hall -  is said to have had a variety of ghostlike experiences. One is that when there was only one student in the entire dorm during the summer, she heard childlike singing and the piano playing and after going to investigate she found all of the sinks turned in all of the rooms on her corridor. It is also said that mysterious child-sized handprints appear on the outside of third floor windows.", "country ": "United States", "longitude ": "-93.1828167", "latitude ": "44.4617681", "state_abbrev ": "MN", "jaccard_score": 0.00017297773304818215}