{"description ": "Loud roars, yells, and screams in the surrounding woods throughout the whole road. A very bright, white, flowing entity walks up and down the road. Said to be a woman by the name of Julia that was murdered by an unidentified man while waiting for her soon-to-be husband. A man that was not permitted to see the woman because her parents despised him.", "state ": "Florida", "latitude ": "28.9124945", "country ": "United States", "location ": "Rolling Acres Road", "longitude ": "-81.936858", "city ": "Lady Lake", "state_abbrev ": "FL", "city_longitude ": "-81.92286039999999", "id": "164773da-c001-40e7-bce3-ea44f8085d7f", "city_latitude": "28.9174855", "jaccard_score": 0.00017297773304818215}