{"longitude ": "-92.1582244", "state_abbrev ": "AR", "id": "16f022a0-0635-4e88-a410-ce8d2143054c", "latitude ": "34.8836823", "city ": "Jacksonville", "country ": "United States", "city_longitude ": "-92.1101458", "description ": "The Band Room is haunted by two band students that had passed away years ago. The doors open by themselves and random percussion instruments, especially the wind chimes are heard, although no one is playing them.", "state ": "Arkansas", "location ": "North Pulaski High School", "city_latitude": "34.8662005", "jaccard_score": 0.00017297773304818215}