{"longitude ": "", "state ": "Michigan", "city_latitude": "45.64695630000001", "location ": "Hikyes Tomb", "id": "1a48acfa-c059-48c9-82ee-5d638f9bc962", "country ": "United States", "state_abbrev ": "MI", "city ": "Cheboygan", "latitude ": "", "description ": "An old farmer went insane and killed his family and then himself. If you go out to the site at night you feel overwhelmed by fright. And never take a stone from the tomb you will be dealt with in a not so nice matter. 2 people drove over the tomb on purpose and there truck just died for no reason. There friends in a car behind them had the steering wheel jerked and they crashed into a tree.", "city_longitude ": "-84.4744795", "jaccard_score": 0.0001572524845892565}