{"state_abbrev ": "CT", "latitude ": "29.987146", "description ": "haunted by a woman who used to live there. It was a mansion converted into a restaurant in the mid 60's. Now the story is, that she lived there with her brother for many years, but they rarely spoke, and they say, for this reason, she haunts this place.", "city ": "Seymour", "id": "24ed51cc-057c-4433-94e1-3f0a265a6a3f", "country ": "United States", "longitude ": "-90.098917", "city_latitude": "41.397146", "location ": "Carousel Gardens", "state ": "Connecticut", "city_longitude ": "-73.07475339999999", "jaccard_score": 0.00017297773304818215}