{"state ": "New York", "city ": "Rochester", "state_abbrev ": "NY", "description ": "A young boy died driving drunk when he was only a junior. He died and now is reported haunting the school. Looking for his girlfriend. Who at the time was pregnant with his baby. At night many see him speeding around the school.", "longitude ": "-77.7061148", "country ": "United States", "id": "25b1c7a2-24bd-4483-a638-d0275cbb77f8", "location ": "Gates Chili High School", "city_longitude ": "-77.6109219", "latitude ": "43.1544782", "city_latitude": "43.16103", "jaccard_score": 0.00017297773304818215}