{"longitude ": "-77.6305552", "location ": "Holy Sepulchre Cemetery", "state ": "New York", "city ": "Rochester", "state_abbrev ": "NY", "country ": "United States", "latitude ": "43.2133267", "city_longitude ": "-77.6109219", "description ": "you can see ghostly apparitions of dark shadowy woman in black, and in the children's section, you can find white figures that look like smoke almost.", "id": "30e2b748-6a1b-4185-8714-565ece9920d6", "city_latitude": "43.16103", "jaccard_score": 0.00017297773304818215}