{"location ": "7 Steps", "state_abbrev ": "PA", "latitude ": "41.6580848", "longitude ": "-76.6962207", "country ": "United States", "description ": "an old railroad tunnel with 7 large steps leading up to the top. It is said that a boy was riding through on his bike and was hit by the train and now still haunts the tunnel. Some nights he will appear, but there are always sounds of train whistles, footsteps, and little kid laughing.", "city_latitude": "41.656464", "id": "322208cf-c8bd-48f2-a96f-fb9efe13a293", "city_longitude ": "-76.8532927", "city ": "Canton", "state ": "Pennsylvania", "jaccard_score": 0.00017297773304818215}