{"longitude ": "", "id": "42ae358e-e399-4959-85d3-c3111ba3ae99", "description ": "There are reports of items being moved from one place and found in different areas of home.\u00a0 There are frequent noises like footsteps and the sound of bells ringing.\u00a0 There was two eye-witnesses who encountered someone or something tossing a lit candle across the room in the upstairs of the home.", "location ": "Y-NOTSHOP", "city_longitude ": "-89.6712008", "state ": "Illinois", "country ": "United States", "city_latitude": "38.7394918", "latitude ": "", "city ": "Highland", "state_abbrev ": "IL", "jaccard_score": 0.0001572524845892565}