{"city_longitude ": "-78.48288219999999", "description ": "Devereux Hall - The top floor of this residence hall was supposedly closed after a s\u00e9ance held by students went too far and someone died. Students say they can hear noises coming from the floor. Students have also reported seeing a ghost jogger who runs up and down the halls.", "city_latitude": "42.0784113", "state ": "New York", "state_abbrev ": "NY", "location ": "St. Bonaventure University", "country ": "United States", "latitude ": "42.0784113", "city ": "St. Bonaventure", "id": "4489e862-fa35-464c-a65e-79eaeae2a471", "longitude ": "-78.48288219999999", "jaccard_score": 0.00014152723613033085}