{"longitude ": "-86.23470429999999", "state ": "Tennessee", "description ": "Hastings entertainment store and a tsc - formerly - Old Walmart Building - Night shift crew would see black apparitions out of the corner of their eye, report being tapped on the shoulder or pinched on their backside. There where reports of seeing merchandise move off pallets, fall of shelves and items disappear to reappear nowhere near where the where to begin with. Strange music being played, seeing strange faces in the security balls that hang on the ceiling. Hearing screams and strange voices over the PA system. This store is no longer the Wal-Mart, since it moved to a Supercenter.", "state_abbrev ": "TN", "latitude ": "35.3841517", "id": "4ab3fed3-e3b8-45b8-bb4e-c8941683ffda", "country ": "United States", "city ": "Tullahoma", "city_latitude": "35.3620235", "city_longitude ": "-86.20943419999999", "location ": "Forest Gallery Shopping Center", "jaccard_score": 0.00017297773304818215}