{"id": "63df0f53-b819-4fe9-a129-b95c79053e06", "longitude ": "-83.96416339999999", "state ": "Tennessee", "city ": "Maryville", "city_latitude": "35.7564719", "state_abbrev ": "TN", "city_longitude ": "-83.9704593", "country ": "United States", "latitude ": "35.7514166", "description ": "Wilson Chapel - It is said that Lily, a shy woman who worked behind the scenes in the drama department, was left by her lover for the star of the show. It is said that she continues this tradition and can be seen in the catwalks above the stage in her favorite black and white dress.", "location ": "Maryville College", "jaccard_score": 0.00017297773304818215}