{"location ": "Young's Park", "latitude ": "37.7556422", "id": "67417448-4364-4f04-b268-2129cea7b89e", "city_longitude ": "-84.8432852", "country ": "United States", "state ": "Kentucky", "longitude ": "-84.84815929999999", "city_latitude": "37.762298", "city ": "Harrodsburg", "state_abbrev ": "KY", "description ": "Young's Park was the site of a ball in late 1800s. A young woman is said to have danced herself to death. Her grave is still there, and marked UNKNOWN. People have reported seeing her dancing there late at night.", "jaccard_score": 0.00017297773304818215}