{"state_abbrev ": "CT", "latitude ": "41.5267705", "city ": "Colchester", "city_longitude ": "-72.3320051", "id": "746d037b-ed33-44f2-8a8a-54c034a75643", "country ": "United States", "city_latitude": "41.5756728", "location ": "Camp Connecticut", "longitude ": "-72.2185437", "description ": "in pictures taken there are many \"orbs\" near the main gate and near the large sign within the camp, examinations shown not be photo error or bad development. Witnesses have seen 40 apparitions standing in front of the gate, as they walked towards them they parted, letting them though, and they walked right in between them. as the got to their car the figures slowly disappeared.", "state ": "Connecticut", "jaccard_score": 0.00017297773304818215}