{"id": "78702abe-eaa6-4d6c-9683-c49673b9c6bc", "state ": "California", "longitude ": "-117.458549", "city ": "Riverside", "state_abbrev ": "CA", "location ": "Indian Hills", "description ": "The Avilas House - The Avilas House is an old mansion located in Indian Hills. At night, there have been sightings of an old woman walking the hallways and knocking on the door to the laundry room.", "country ": "United States", "latitude ": "33.986162", "city_longitude ": "-117.3961564", "city_latitude": "33.9533487", "jaccard_score": 0.00017297773304818215}