{"latitude ": "36.918815", "city ": "Fort Story", "location ": "Coast Artillery Rd.", "state_abbrev ": "VA", "city_longitude ": "-76.0173549", "state ": "Virginia", "country ": "United States", "longitude ": "-75.9956658", "id": "8382b108-0e26-4b28-b938-b936166f46fc", "description ": "On the coldest, wettest nights There has been at least two sightings by soldiers who regularly patrol the base of a mysterious ghostly being who allegedly disappears into the wetlands of this area. It has been said that this may be the ghost of a soldier who was stationed here who committed suicide by hanging himself about 5 years ago.", "city_latitude": "36.9231796", "jaccard_score": 0.00017297773304818215}