{"state_abbrev ": "OR", "description ": "people have claimed to here foot steps walk back in forth in the halls. There have been pictures taken and in the pictures there are clearly orbs in the lobby hall. Feelings of a strange presence in the rooms in the middle of the night. Apparitions of a woman have been reported.", "longitude ": "-121.174411", "location ": "New Redmond Hotel", "latitude ": "44.2720716", "city_longitude ": "-121.1739212", "country ": "United States", "state ": "Oregon", "city ": "Redmond", "id": "8efde359-d10a-4029-b711-915e6ba67f5e", "city_latitude": "44.2726203", "jaccard_score": 0.00017297773304818215}