{"description ": "Chaminade University - A sophomore at the school was killed in a car accident a few years ago. Sometimes at night you can hear him skateboarding around the dorm room. He is most often heard on Halloween because that was his favorite holiday.", "id": "b0ec815c-c2ee-4a12-834c-6e6f2b442370", "location ": "Waialae", "city_longitude ": "-157.8583333", "state_abbrev ": "HI", "country ": "United States", "state ": "Hawaii", "city ": "Honolulu", "longitude ": "-157.7762165", "latitude ": "21.2705629", "city_latitude": "21.3069444", "jaccard_score": 0.00017297773304818215}