{"id": "cb4f9596-1d05-43e3-984b-17bc3e04ff18", "city_longitude ": "-110.926479", "state ": "Arizona", "city ": "Tucson", "location ": "University of Arizona", "country ": "United States", "longitude ": "-110.9501094", "description ": "English Building - Where the building stands now, used to be a running track years ago. The body of a woman raped and murdered was found in a well at the edge of the track. The apparition of a woman is often seen through the windows of the locked building late at night, running and panicked, perhaps still trying to escape her attacker.", "state_abbrev ": "AZ", "city_latitude": "32.2217429", "latitude ": "32.2318851", "jaccard_score": 0.00017297773304818215}