{"latitude ": "43.5054845", "city ": "Mission", "id": "d26e846a-d44c-4beb-a158-1d5ed3b90f32", "country ": "United States", "longitude ": "-96.6765314", "state ": "South Dakota", "description ": "This is located on a stretch of gravel road 1 mile north of Mission, This dirt road is believed to be haunted by the spirits of dead Indian women and children who were running for their lives and were slain by pioneers. To this day, it is said that you can see the ghosts and hear their screams and warnings.", "location ": "\"Rock Hill\"", "state_abbrev ": "SD", "city_longitude ": "-100.6581944", "city_latitude": "43.3058368", "jaccard_score": 0.00017297773304818215}