{"city_longitude ": "-90.822871", "description ": "Its been told that you can see lights go on in the old plantation houses, and see people walking around jus' like in the olden days when they had the slaves back there", "state ": "Louisiana", "city_latitude": "29.7957633", "latitude ": "29.78992", "country ": "United States", "city ": "Thibodaux", "id": "d99472c1-382c-47bc-9826-ba0659d49c6d", "state_abbrev ": "LA", "location ": "Laural Valley Plantation Rd.", "longitude ": "-90.7867328", "jaccard_score": 0.00017297773304818215}