{"state ": "Massachusetts", "latitude ": "42.4981591", "location ": "The Middle School", "country ": "United States", "longitude ": "-70.86181909999999", "description ": "In the girls' locker room there is a ghost of a young man who died in a motorcycle and now he haunts the girl room. Also there was a report of UFOs over the school it was even in the local news paper there was a photo of the UFOs. The town of Marblehead was built on a psychical portal a sort of window that lets in both negative and positive spiritual energy, a \"hellmouth\" as it was called in the 17th century.", "state_abbrev ": "MA", "id": "e4c594a2-8680-4f91-b832-4ac56b7677f5", "city ": "Marblehead", "city_latitude": "42.49995819999999", "city_longitude ": "-70.8578024", "jaccard_score": 0.00017297773304818215}