{"description ": "These woods are said to be haunted. The occurrences seem to take place mainly around a house off Pollock Road. It is located in the middle of the woods on your right. Witnesses have reported seeing light orbs and strange eyes without a face in the darkness. Some people have even claimed to hear someone singing.", "city ": "Latham", "state ": "New York", "latitude ": "42.781408", "state_abbrev ": "NY", "location ": "Guptills Woods on Pollock Road", "country ": "United States", "city_latitude": "42.7477661", "longitude ": "-73.744764", "id": "e6fdf474-6cbc-4434-8a6a-1f5b4b9040ba", "city_longitude ": "-73.760537", "jaccard_score": 0.00017297773304818215}