{"city_longitude ": "-102.2415477", "latitude ": "43.9901699", "description ": "There is sometimes footsteps heard from the roof (which is three stories up and has no stairwell leading to it). Then the footsteps stop and a soft thud is heard. This happens every year at 11:30 at night on December the twenty forth. Some call it the Santa Claus Ghost. But others believe that it was a principal that died in a freak electrical fire and was burned to death in 1930.", "country ": "United States", "city_latitude": "43.9924889", "longitude ": "-102.2477733", "state ": "South Dakota", "city ": "Wall", "id": "f5f85b37-47de-4cdb-be0a-bb71aa5344c3", "state_abbrev ": "SD", "location ": "Wall High School", "jaccard_score": 0.00017297773304818215}