{"latitude ": "38.1919879", "description ": "There was supposed to have been a little boy who lived in the house next to the creek under the trestles. He went out one day to watch a train go by from the top of the hill and fell onto the tracks, he was then run over. If you drive under the trestles right at dusk, you can see his blue shirt blowing in the wind stuck in the middle of the tracks, and him waving to you from the tracks.", "city_longitude ": "-85.4718869", "city_latitude": "38.19148500000001", "id": "f8fe761f-37ca-4b33-98ff-4e667baf2855", "location ": "The Trestles", "country ": "United States", "state ": "Kentucky", "city ": "Fisherville", "state_abbrev ": "KY", "longitude ": "-85.4881559", "jaccard_score": 0.00017297773304818215}