{"state ": "California", "longitude ": "-117.1932703", "city_latitude": "32.715738", "state_abbrev ": "CA", "city ": "San Diego", "id": "fd7a29a2-82e7-4b46-b4a5-c9eec88c383d", "country ": "United States", "description ": "Formerly posted as \"Old Town Cemetery\" - This was partially paved over with a road. It is said ghosts appear to be crossing that section of the road at night. - February 2004 Correction: The proper name of the \"Old Town Cemetery\" in San Diego is \"El Campo Santo Cemetery.\" Among the numerous other spirits sighted at the location (including the paved portions under the adjacent sidewalk and streets), psychics claim that the site is to this day overseen by the spirit of the gravedigger whose own grave is near the cemetery's SE corner.", "latitude ": "32.7516073", "location ": "El Campo Santo Cemetery", "city_longitude ": "-117.1610838", "jaccard_score": 0.00017297773304818215}