{"longitude ": "-104.4516098", "city_longitude ": "-104.4521747", "city ": "Lusk", "city_latitude": "42.7624668", "location ": "The Yellow Motel", "country ": "United States", "latitude ": "42.7587364", "state ": "Wyoming", "id": "cee2b426-da59-46ec-b0b0-2886d985fa58", "description ": "The motel was a brothel during the latter part of the 19th century into the early 20th century.\u00a0 Strange lights have been seen.\u00a0 Voices and overall strange feelings overcome you in the building.", "state_abbrev ": "WY", "jaccard_score": 0.00017297773304818215}