{"latitude ": "41.9753731", "city ": "Bertram", "state_abbrev ": "IA", "id": "39d75c13-eefc-4176-a450-4414208b4de5", "location ": "Campbell Cemetery", "state ": "Iowa", "city_latitude": "41.9497259", "country ": "United States", "longitude ": "-91.5393245", "description ": "Trunkless Tree - If you go there at night and shut off your headlights there is a tree that looks like it is floating and has no base to it.? There used to be two trees right next to each other that looked that way but one was cut down.", "city_longitude ": "-91.5354538", "jaccard_score": 0.00017297773304818215}