{"city_longitude ": "-83.7524298", "longitude ": "-83.761111", "state_abbrev ": "OH", "country ": "United States", "latitude ": "40.100596", "id": "3ae061a3-58bb-4654-84ac-2454fdc85657", "description ": "North Hall - train tracks - Haunted by a woman named rose for the smell that accompanies her., and on the train tracks there have been reports of a spectral train.", "state ": "Ohio", "location ": "Urbana University", "city_latitude": "40.1083912", "city ": "Urbana", "jaccard_score": 0.00017297773304818215}