{"location ": "Moses Lake High School", "id": "8067237d-8b1a-4d82-a2d7-d3f21a331a82", "city_latitude": "47.1301417", "city_longitude ": "-119.2780771", "description ": "Theater - In the theatre the curtains sway when no one is there. The lights turn on when there is no one there. There is a cat walk above the seats where they can be heard swaying when the door to the stairway is locked tight, and the stairs creak also when the door is locked tight. When you go to the costume room you can feel the atmospheric imprint of people there.", "country ": "United States", "latitude ": "47.1117297", "longitude ": "-119.2658505", "state ": "Washington", "state_abbrev ": "WA", "city ": "Moses Lake", "jaccard_score": 0.00017297773304818215}