{"description ": "no known denomination. It has two stories, but only the first is accessible. The windows are painted blood red, even on the 2nd floor. Now abandoned, the place is still heavily guarded by pure evil, evident through spectral photos.", "latitude ": "35.4231307", "state ": "Tennessee", "state_abbrev ": "TN", "city_latitude": "35.6150716", "location ": "Bear Creek Church", "country ": "United States", "id": "7c81265e-c6c8-4cfa-ac69-6ef00d0d48bb", "city ": "Columbia", "city_longitude ": "-87.0352831", "longitude ": "-86.93194799999999", "jaccard_score": 0.00017297773304818215}