{"state_abbrev ": "WV", "city ": "Hamlin", "city_longitude ": "-82.1029156", "city_latitude": "38.2787019", "description ": "Slone Cemetery - There is the presence of a strange woman. She comes up behind you and blows on your ears. Sometimes she will even whisper a request. There are also two babies named Faith and Hope. You can hear giggling and crying. Sometimes, they can even be seen.", "country ": "United States", "latitude ": "38.2442268", "location ": "Isaac", "id": "7cd9ff3e-c038-4dee-8539-46e5136da3e0", "longitude ": "-82.16371459999999", "state ": "West Virginia", "jaccard_score": 0.00017297773304818215}