{"state ": "Missouri", "location ": "Heartland Health Care Center", "description ": "Some former residents that have passed on come back on nights that another resident passes on. Sometimes they can be heard and shadows seen.", "city ": "Cape Girardeau", "city_latitude": "37.3058839", "country ": "United States", "longitude ": "-89.573549", "latitude ": "37.348565", "state_abbrev ": "MO", "id": "9781c9b8-8710-47f2-8acc-cd621b3cb649", "city_longitude ": "-89.51814759999999", "jaccard_score": 0.00017297773304818215}