{"city_latitude": "33.4734978", "longitude ": "-82.0229739", "state_abbrev ": "GA", "id": "97b69e37-e51c-41bf-b713-c476beeea3f0", "country ": "United States", "location ": "Augusta State University", "state ": "Georgia", "city_longitude ": "-82.0105148", "description ": "Bellevue Hall - The ghost of Emily Galt is said to haunt the building. Emily etched her name (\"Emily Galt, 1816\") in the glass of one of the windows before her fianc\u00e9 left and was killed, in the Civil War. Finding out her betrothed was dead; she threw herself out of one of the upper windows, and died. It's said at night you can hear the two lovers arguing over whether or not he should go off to battle. Phones and TVs mysteriously go haywire. The widow still exists and is in storage at the university.", "city ": "Augusta", "latitude ": "33.4758562", "jaccard_score": 0.00017297773304818215}