{"city ": "Orlando", "latitude ": "28.385233", "longitude ": "-81.563874", "state ": "Florida", "country ": "United States", "city_longitude ": "-81.3792365", "id": "4120ff03-c1c6-4cd6-90df-af15da9b0cec", "description ": "EPCOT - Spaceship earth - a small girl with long blonde hair has been seen riding in a car & a boy run in front of her and vanish at the same location (outside during the day).", "location ": "Walt Disney World", "state_abbrev ": "FL", "city_latitude": "28.5383355", "jaccard_score": 0.00017297773304818215}