{"state ": "California", "description ": "Colossus - there's supposedly a child in a striped shirt who occasionally can be seen at night running through the supports underneath Colossus. That, and sometimes at night the lift chain can be heard running and the clanking of the anti-rollbacks, despite the ride being shut down for the night.", "location ": "Six Flags", "state_abbrev ": "CA", "id": "cb5a7425-7491-4453-a2cb-56b94f0347cc", "city_longitude ": "-118.5713823", "country ": "United States", "latitude ": "34.4253305", "city ": "Valencia", "longitude ": "-118.5972191", "city_latitude": "34.456151", "jaccard_score": 0.00017297773304818215}