{"location ": "Prince Georges county", "state ": "Maryland", "city ": "Greenbelt", "id": "ee402b37-1946-41fc-8d06-c885d75c2ef5", "description ": "NASA/GSFC - Bldg #22 - feels like some one is playing games with you! Reports of a death in the early years of the center in this building!", "longitude ": "-76.87552819999999", "city_longitude ": "-76.87552819999999", "country ": "United States", "city_latitude": "39.0045544", "latitude ": "39.0045544", "state_abbrev ": "MD", "jaccard_score": 0.00014152723613033085}