{"state ": "California", "city ": "Palos Verdes", "location ": "Light House", "longitude ": "-118.4099042", "state_abbrev ": "CA", "latitude ": "33.7422359", "country ": "United States", "id": "001cf5c5-ac2f-4df4-81ab-ad18dc315557", "city_latitude": "33.7444613", "city_longitude ": "-118.3870173", "description ": "It was something to do with a lady and her baby. Possibly, they used to be the keepers of the lighthouse. Rumor is she killed her baby then committed suicide. People say that if you go there at night you can either see her or hear a woman screaming.", "jaccard_score": 0.00017297773304818215}