{"longitude ": "-80.343718", "latitude ": "35.5129693", "id": "80869070-c9f3-4d3b-8438-e95b999714f7", "description ": "On Richfild rd you can stop and put your car in neutral and it will roll up the hill. They say there was a baby and her mom staled the car. She tried to push it off the road but a truck hit and killed them both. And if you put baby powder on the back of your car you will see hand prints in it", "city_longitude ": "-80.33811349999999", "country ": "United States", "state ": "North Carolina", "state_abbrev ": "NC", "location ": "Gravity Hill", "city ": "Gold Hill", "city_latitude": "35.5212509", "jaccard_score": 0.00017297773304818215}