{"state ": "California", "city_latitude": "39.445723", "id": "998fe037-d50d-4292-87f9-4ec4ecc841d4", "state_abbrev ": "CA", "longitude ": "-123.805562", "country ": "United States", "city_longitude ": "-123.8052935", "latitude ": "39.449865", "description ": "has a chair that has had eerie happenings the lady that owns the inn has said that people had died mysteriously and not long after they had sat in the chair.", "city ": "Fort Bragg", "location ": "Glassbeach Inn", "jaccard_score": 0.00017297773304818215}