{"longitude ": "-77.358437", "latitude ": "34.72295", "city ": "Havelock", "country ": "United States", "location ": "Halliburton naval hospital", "state ": "North Carolina", "state_abbrev ": "NC", "city_longitude ": "-76.9013301", "description ": "cherry point - On February 1 around 2 am an overnight rn was at the snack/drink machines in the hospital when she saw a person dressed in all black run by the doorway, within seconds she was at the door to see there was no one in the hall, nor had she heard anyone running down the hall she was the only one there.", "id": "64f58517-70bc-4663-a2d3-eb0add72092f", "city_latitude": "34.8790492", "jaccard_score": 0.00017297773304818215}