{"latitude ": "41.8408039", "id": "042e9335-d031-4f81-b038-0c41e03bf565", "city ": "Rehoboth", "state ": "Massachusetts", "longitude ": "-71.2610644", "country ": "United States", "city_longitude ": "-71.2393933", "location ": "Cemetery off route 44", "description ": "Feelings of being unwanted. Haunted by an old man that screams and pounds on your car windows as they sped out of the cemetery. While he terrorizes visitors, calling them Catherine. A girl\u2019s laugh was heard toward the Woods on the right.", "state_abbrev ": "MA", "city_latitude": "41.8470056", "jaccard_score": 0.00017297773304818215}