{"city_longitude ": "-111.9391023", "longitude ": "-111.944385", "state ": "Utah", "city_latitude": "40.521893", "id": "2f59fbbd-3dd3-4fef-8959-100560e8b9c0", "city ": "Riverton", "description ": "late at night you can hear children\u2019s voices you can hear footsteps behind you. in the boiler room you can hear a little girl crying, because she fell down a shoot.", "country ": "United States", "state_abbrev ": "UT", "latitude ": "40.512258", "location ": "old Riverton Elementary", "jaccard_score": 0.00017297773304818215}