{"state ": "Alabama", "id": "314644b8-8a80-4daa-b01c-2e904ad7a2a7", "description ": "A woman was walking down the side of Highway 5 near the Winston County Drag Strip. She was run over and killed by an 18-wheeler. Her ghost now jumps onto the side of 18-wheelers looking for the driver that ran her over.", "state_abbrev ": "AL", "country ": "United States", "city ": "Lynn", "latitude ": "34.0524363", "location ": "Highway 5", "longitude ": "-87.5493831", "city_latitude": "34.0470483", "city_longitude ": "-87.54974", "jaccard_score": 0.00017297773304818215}