{"id": "315aff97-2925-4bcc-bdf4-15ddec10f6db", "city_longitude ": "-96.2800116", "state_abbrev ": "NE", "state ": "Nebraska", "longitude ": "-96.3125307", "city_latitude": "40.925555", "country ": "United States", "description ": "People will be walking through the cemetery looking at children\u2019s graves and begin to hear many children playing out in the road and go to look and no one is there.", "location ": "Oxbow Cemetery", "latitude ": "40.9142957", "city ": "Murdock", "jaccard_score": 0.00017297773304818215}