{"city_latitude": "32.3199396", "longitude ": "-106.802703", "location ": "toys -r -us", "latitude ": "32.3120081", "city ": "Las Cruses", "state_abbrev ": "NM", "country ": "United States", "description ": "a little boy about five or six years old haunts the store in the night you could here his laughs and during the day has always playing with the toys so employees have a hard time keeping the toys off the floor. - October 2007 Update: Store has now been closed and abandoned for most of a year. Was shut down as part of Toys r us financial problems.", "id": "c5b58908-6642-471b-9beb-d7f7f3b4f3e1", "state ": "New Mexico", "city_longitude ": "-106.7636538", "jaccard_score": 0.00017297773304818215}