{"longitude ": "", "state ": "Minnesota", "id": "550dd0b8-a444-476b-a48d-15759e6809e0", "city ": "Sherack", "location ": "Highways around town of Sherack", "country ": "United States", "city_longitude ": "-96.7817329", "description ": "A man is seen hitchhiking during on dark, stormy, rainy nights. Many people report picking up the hitchhiker and later turning to him in the car only to find he's not there.", "latitude ": "", "city_latitude": "48.0208078", "state_abbrev ": "MN", "jaccard_score": 0.0001572524845892565}