{"description ": "There are two ghosts on campus. 1. Alice, a ghost who is suppose to haunt the Joe E. Brown theater on campus. 2. Amanda, a ghost who is suppose to haunt the Chi Omega Sorority house on campus.", "state_abbrev ": "OH", "city_latitude": "41.3747744", "city ": "Bowling Green", "city_longitude ": "-83.6513229", "country ": "United States", "id": "d888cb54-9cdc-4234-bd3f-c9af9776371e", "location ": "State University", "latitude ": "41.3797788", "state ": "Ohio", "longitude ": "-83.6300826", "jaccard_score": 0.00017297773304818215}