{"city_latitude": "41.8566676", "city_longitude ": "-89.1134166", "latitude ": "41.823257", "location ": "Reynolds Cemetery", "state_abbrev ": "IL", "state ": "Illinois", "country ": "United States", "city ": "Reynolds Township", "longitude ": "-89.1508032", "id": "0960c9c8-d071-4539-bb49-89d7c1d635a0", "description ": "In the rear of the cemetery there is the small grave of a baby boy. The baby was abandoned and found weeks later and the mother was never caught. On a full moon at exactly midnight you can feel his heartbeat if you lay your hand on his stone.", "jaccard_score": 0.00017297773304818215}