{"state ": "Wisconsin", "longitude ": "-88.60079060000001", "city_longitude ": "-88.5995456", "city ": "Walworth", "country ": "United States", "state_abbrev ": "WI", "location ": "Walworth Grade School", "description ": "It is said a janitor that fell down the steps to the boiler room haunts the school. He doesn't harm anyone, but doesn't know how to leave the school.", "latitude ": "42.5300764", "id": "7bcb9906-8463-4ef7-8961-98630a845ac8", "city_latitude": "42.5311279", "jaccard_score": 0.00017297773304818215}