{"city_latitude": "38.3640795", "state ": "California", "state_abbrev ": "CA", "location ": "rail road crossing", "latitude ": "38.3501481", "city_longitude ": "-122.5241487", "country ": "United States", "longitude ": "-122.5120208", "city ": "Glen Ellen", "description ": "It's said that in Glen Helen by the rail road tracks if you put your car in neutral with your car not facing the rail road tracks and wait two through three minutes it is said that the ghosts of six kids will start to push your car slowly at first, then with a rapid speed they will try to get you to the tracks, if you try to stop, it is difficult if they have gained their full speed! You can verify this by driving to the nearest gas station and if you look closely you can see their little hand prints!", "id": "7bf6a31a-bf0a-4ff4-99a7-1ef52b4e88d8", "jaccard_score": 0.00017297773304818215}