{"location ": "Haverhill Graveyard", "city ": "Haverhill", "id": "daae81b6-c9b6-4c74-ad5b-b8707227ad10", "latitude ": "42.7722484", "city_latitude": "42.7762015", "state ": "Massachusetts", "description ": "There is a graveyard in Haverhill, MA that houses the grave of Lydia Ayer. She is called \"The Woman in White\" and supposedly floats around the graveyard and surrounding areas.", "country ": "United States", "state_abbrev ": "MA", "longitude ": "-71.0652771", "city_longitude ": "-71.0772796", "jaccard_score": 0.00017297773304818215}