{"longitude ": "-77.3669487", "city ": "Richmond", "city_latitude": "37.5407246", "state_abbrev ": "VA", "latitude ": "37.4689282", "state ": "Virginia", "location ": "Pocohantas Parkway", "country ": "United States", "description ": "The new road was constructed over an old Indian Grave.\u00a0 Spirits come out around midnight near the tollbooth.\u00a0 There have been several reports of the spirits to the police.\u00a0 Toll booth workers say they hear strange noises at night.", "id": "59ec7367-fddb-4688-98a1-9edc14a15350", "city_longitude ": "-77.4360481", "jaccard_score": 0.00017297773304818215}