{"location ": "Big Bamboo Lounge", "latitude ": "28.333475", "state ": "Florida", "country ": "United States", "description ": "Ladies bathroom toilets flush by its self you have a feeling that their is some one else in the bathroom with you but no one else is there also the employees could be alone working and thing move by its self chairs glasses and lights. - April 2008 Update: Has been torn down.", "city ": "Kissimmee", "city_latitude": "28.2919557", "longitude ": "-81.4766339", "city_longitude ": "-81.40757099999999", "state_abbrev ": "FL", "id": "507458ec-838c-450f-a0b7-ee49487f9955", "jaccard_score": 0.00017297773304818215}