{"latitude ": "39.4769444", "state_abbrev ": "IN", "city ": "Terre Haute", "location ": "Highland Lawn Cemetery", "country ": "United States", "city_longitude ": "-87.41390919999999", "description ": "Just the old story of Stiffy Green. Supposedly Stiffy (a dog) and his dead master can be seen walking in the cemetery at night. February 2005 Update/Correction: Stiffy Green did not roam the cemetary, but instead was inside the mausoleum of his owner. He was removed several years ago because the cemetary didn't want kids driving through the cemetary late at night.", "id": "b678b8e6-8a67-440c-b044-07e95c6ccb47", "longitude ": "-87.3484221", "city_latitude": "39.4667034", "state ": "Indiana", "jaccard_score": 0.00017297773304818215}