{"latitude ": "41.7520612", "country ": "United States", "location ": "Kickemuit River", "city_latitude": "41.7303793", "id": "f3d7f425-080f-4cf5-988d-652c4d256998", "state ": "Rhode Island", "city ": "Warren", "state_abbrev ": "RI", "longitude ": "-71.24584329999999", "description ": "School house roads - It is said that there are seven haunted heads there if u go at the right time u can see them. The head are seen floating above seven poles where they were posted as a warning to all English pioneers not to go on the land. this warning was put up by the Native Americans that didn\u2019t want the English invading.", "city_longitude ": "-71.2825493", "jaccard_score": 0.00017297773304818215}