{"longitude ": "-103.4808384", "location ": "Villa Theresa Guest House", "latitude ": "43.4373781", "city ": "Hot Springs", "country ": "United States", "state ": "South Dakota", "city_longitude ": "-103.4743625", "city_latitude": "43.431646", "description ": "This historic inn has a very colorful past. The scent of perfume lingers around the upstairs dormer rooms. Visions have been seen at the main staircase. The spirit of a girl by the name of Giselle happily roams the household. A very inviting and non-threatening mystery.", "state_abbrev ": "SD", "id": "8ffae666-574e-4d08-826a-670b49db2b3e", "jaccard_score": 0.00017297773304818215}