{"latitude ": "39.4805565", "location ": "Oxford state road", "city_latitude": "39.5069974", "longitude ": "-84.4206091", "id": "6017933e-de0e-4095-8863-9051f7f256fe", "state_abbrev ": "OH", "description ": "If you are parked at the top of the hill and flash your lights three times you will see a motorcycle come toward you. Legend has it a guy and a girl were not allowed to see each other so the girl would sneak out at night and flash a light three times. To the her boyfriend waiting at the top of the road. But one night she flashed the lights and he started toward her house, but wrecked on the way and died. So now when you flash you lights he thinks that it is his girlfriend and he starts to come down the road.", "country ": "United States", "city ": "Oxford", "state ": "Ohio", "city_longitude ": "-84.74523099999999", "jaccard_score": 0.00017297773304818215}