{"id": "6601eb5d-cee3-4f2d-9787-43561bc2ff47", "description ": "If you steer in to the voke park baseball field you will notice a lil'boy that got viseously attacked by 2 dogs. He seen wearing the same clothes he was on the night of his death,and bloody and asking for help ,rumor has it when you approach him he dissapears.", "state ": "Massachusetts", "longitude ": "-71.0313906", "city_latitude": "42.3917638", "country ": "United States", "state_abbrev ": "MA", "city_longitude ": "-71.0328284", "location ": "Voke Park", "city ": "Chelsea", "latitude ": "42.4090178", "jaccard_score": 0.00017297773304818215}