{"latitude ": "40.1042481", "state ": "Utah", "location ": "Spanish Fork Cemetery", "city_latitude": "40.114955", "country ": "United States", "longitude ": "-111.6482094", "city_longitude ": "-111.654923", "state_abbrev ": "UT", "id": "fb39bb33-960a-4e9b-8e06-0d4f98b3e771", "city ": "Spanish Fork", "description ": "In the Spanish Fork Cemetery.\u00a0 There is a headstone stature of a woman; she is crouched down with one arm extended and the other near her face.\u00a0 She is known as the Weeping Willow or Widow, depending on whom you hear it from.\u00a0 But if you go there after dark, it is said that the statue will actually cry, tears stream down her face.\u00a0 There are old water markings still on the statue.\u00a0 And sometimes you can hear her crying and calling for her baby.", "jaccard_score": 0.00017297773304818215}