{"city_latitude": "36.7253755", "longitude ": "-82.69168049999999", "state_abbrev ": "VA", "city_longitude ": "-82.6962702", "state ": "Virginia", "country ": "United States", "id": "d43be59e-a214-4bad-806b-955e5fd0bf99", "city ": "Rye Cove", "latitude ": "36.7321295", "location ": "Nashville Music Institute", "description ": "building is located on McMillian St off of Church St in Nashville, TN. This building is supposedly the 2nd oldest in Nashville and operated as a prison ran by Sam Houston years ago. In the early 2000's it operated as Nashville Music Institute where many musicians had ghostly experiences.", "jaccard_score": 0.00017297773304818215}