{"state ": "Texas", "description ": "A boy died in the cemetery and he was afraid of the dark so his mother sat at his grave every night for a year holding a lantern. Then she died and every night the light would still appear. From time to time the lantern still appears in the far corner of the cemetery.", "city ": "Kilgore", "longitude ": "-94.7880413", "city_longitude ": "-94.8757709", "country ": "United States", "city_latitude": "32.3862619", "latitude ": "31.8442934", "id": "1e59da7f-3e07-4f24-931d-b129141db719", "location ": "Pirtle Cemetery", "state_abbrev ": "TX", "jaccard_score": 0.00017297773304818215}