{"longitude ": "-73.41868529999999", "city ": "West Stockbridge", "description ": "Campers and counselors have reported seeing apparitions walking across the large field late at night. Also, when camping on the top of blueberry hill, campers and counselors have reported seeing the same apparitions atop at the clearing.", "latitude ": "42.296577", "state ": "Massachusetts", "city_longitude ": "-73.3677582", "city_latitude": "42.3338097", "country ": "United States", "location ": "Camp Kingsmont/Blueberry Hill", "state_abbrev ": "MA", "id": "848e9f75-692e-4ac4-b40a-ab8ccb298a55", "jaccard_score": 0.00017297773304818215}