{"latitude ": "43.00209479999999", "city_latitude": "43.0166806", "location ": "Mitchell Manor Senior Center", "state ": "Wisconsin", "longitude ": "-87.97967129999999", "description ": "Part of this facility is the former summer home to Billy Mitchell's family.\u00a0 Staff has heard voices and felt something brush past them.", "country ": "United States", "state_abbrev ": "WI", "city ": "West Allis", "city_longitude ": "-88.0070315", "id": "282a419d-48af-4ac3-bc91-356c90375fd2", "jaccard_score": 0.00017297773304818215}