{"state ": "Alabama", "city_longitude ": "-86.8436124", "city_latitude": "34.1748208", "latitude ": "34.2429261", "location ": "Vinemont", "state_abbrev ": "AL", "id": "765f9c06-6c59-47ea-9338-f4fc2daaf9bf", "country ": "United States", "city ": "Cullman", "longitude ": "-86.8671293", "description ": "Cry Baby Hollow Off Highway 31 North in Cullman County - It is said that when Cullman was being settled, a family in a wagon was crossing the small wooden bridge. A wheel broke off and the wagon turned over, throwing a small baby into the creek, killing it. Since that time, you can hear a baby crying. Also, if you put a candy bar on the bridge, leave and then come back, there will be a bite taken out of it.", "jaccard_score": 0.00017297773304818215}