{"city ": "Woodgate", "description ": "This camp use to be an orphanage. It is said that every cabin there is hunted by one ghost it is also rumored that the lake we swim in is full of dead bodies, that after a child there died they would either throw them in the lake to bury them. Many of the kids have seen apparitions.", "city_longitude ": "-75.1548888", "state ": "New York", "state_abbrev ": "NY", "country ": "United States", "latitude ": "43.535691", "id": "1af086a5-96ab-4d9a-85b0-bd1f0a84efff", "longitude ": "-75.17761519999999", "location ": "Camp Truk Masonic Youth Home", "city_latitude": "43.5203464", "jaccard_score": 0.00017297773304818215}