{"city_latitude": "40.1645785", "latitude ": "40.181287", "description ": "In Howell there are woods that are haunted. 6:00 between 8:00 there are noises coming from the woods. Often there are screams. One time a little girl traveled into these woods and never came back. Sometimes you can hear her say  \u201cHELP PLEASE IT HURTS!\u201d  It is believed that little girl name was Annmarie.", "longitude ": "-74.260392", "state ": "New Jersey", "city_longitude ": "-74.2082671", "location ": "In the woods", "country ": "United States", "city ": "Howell", "id": "f5439271-3c0c-4011-a588-1b3715272715", "state_abbrev ": "NJ", "jaccard_score": 0.00017297773304818215}