{"state ": "Texas", "id": "ed788037-971f-4502-a417-5504d5142da5", "city_longitude ": "-96.3699632", "country ": "United States", "description ": "A&M Consolidated High School- Rumors abound of a very nasty metaphysical presence that walks (or rather floats) in the career technology wing of this newly renovated high school. This presence is supposedly named Toby and several young students have tried unsuccessfully to document this scary and mysterious hauntings.", "latitude ": "30.6175619", "state_abbrev ": "TX", "longitude ": "-96.3079044", "location ": "College Station", "city_latitude": "30.6743643", "city ": "Bryan", "jaccard_score": 0.00017297773304818215}