{"city ": "Franklineville", "city_latitude": "39.61779689999999", "id": "b9a52fbc-0d14-403b-a0e2-90bb1fcbe3ab", "state ": "New Jersey", "country ": "United States", "latitude ": "39.59499750000001", "description ": "The Inn is so large, many ghosts visit the place. The old owner who first opened it\u2026still runs the now empty Inn!- October 2003 Update: Iona Lake Inn was sold and was turned into a Italian Resturant it's called Jake's Italian Restaurant now....", "state_abbrev ": "NJ", "location ": "Iona Lake Inn", "city_longitude ": "-75.080747", "longitude ": "-75.08323899999999", "jaccard_score": 0.00017297773304818215}